LICENSE
MANIFEST.in
README.md
setup.py
django_google_dfp.egg-info/PKG-INFO
django_google_dfp.egg-info/SOURCES.txt
django_google_dfp.egg-info/dependency_links.txt
django_google_dfp.egg-info/requires.txt
django_google_dfp.egg-info/top_level.txt
google_dfp/__init__.py
google_dfp/models.py
google_dfp/views.py
google_dfp/templatetags/__init__.py
google_dfp/templatetags/dfp_tags.py