Metadata-Version: 1.0
Name: django-google-dfp
Version: 0.1a2
Summary: Template tags for Google DFP.
Home-page: https://bitbucket.org/nextscreenlabs/django-google-dfp
Author: Jason Christa
Author-email: jason@zeitcode.com
License: UNKNOWN
Platform: UNKNOWN
Classifier: Environment :: Web Environment
Classifier: License :: OSI Approved :: BSD License
Classifier: Framework :: Django
Classifier: Programming Language :: Python
